palmtree/__init__.py
palmtree/tree.py
palmtree/tests/__init__.py
palmtree/tests/__main__.py
palmtree/tests/helper.py
palmtree/tests/test_tree.py
palmtree/tests/__fixtures__/get_foo.json
palmtree/tests/__fixtures__/foo/baz_1.txt
palmtree/tests/__fixtures__/foo/foo_1.txt
palmtree/tests/__fixtures__/foo/foo_2.txt
palmtree/tests/__fixtures__/foo/bar/bar_1.txt
palmtree/tests/__fixtures__/foo/bar/bar_2.txt
palmtree/tests/__fixtures__/foo/bar/baz/baz_1.txt
palmtree/tests/__fixtures__/foo/bar/baz/baz_2.txt
palmtree/tests/__fixtures__/foo/baz/baz_1.txt
palmtree/tests/__fixtures__/foo/baz/baz_2.txt
palmtree-0.2.1.dist-info/METADATA
palmtree-0.2.1.dist-info/WHEEL
palmtree-0.2.1.dist-info/top_level.txt
palmtree-0.2.1.dist-info/zip-safe
palmtree-0.2.1.dist-info/RECORD
