Metadata-Version: 2.1
Name: palmtree
Version: 0.2.1
Summary: A pretty filesystem tree inspection utility - for Python.
Home-page: https://github.com/grimen/python-palmtree
Author: Jonas Grimfelt
Author-email: grimen@gmail.com
License: MIT
Download-URL: https://github.com/grimen/python-palmtree
Project-URL: repository, https://github.com/grimen/python-palmtree
Project-URL: bugs, https://github.com/grimen/python-palmtree/issues
Keywords: tree,inspect,inspector,debug,debugger,filesystem,fs,file,link,directory,folder,path,meta,colors,pretty
Platform: UNKNOWN
Classifier: Topic :: Software Development :: Libraries
Classifier: Development Status :: 5 - Production/Stable
Classifier: Intended Audience :: Developers
Classifier: License :: OSI Approved :: MIT License
Classifier: Operating System :: POSIX
Classifier: Programming Language :: Python
Classifier: Programming Language :: Python :: 3
Classifier: Programming Language :: Python :: Implementation :: CPython
Classifier: Programming Language :: Python :: Implementation :: PyPy
Requires-Dist: setupextras (>=0.1.5)
Requires-Dist: six (>=1.11.0)
Requires-Dist: rootpath (>=0.1.0)
Requires-Dist: inspecta (>=0.1.0)
Requires-Dist: mybad (>=0.1.0)
Requires-Dist: attributedict (>=0.1.0)
Requires-Dist: colorful (>=0.5.0)
Requires-Dist: colour-runner (>=0.0.5)
Requires-Dist: deepdiff (>=3.3.0)
Requires-Dist: tox (>=3.0.0)
Requires-Dist: coverage (>=4.5.2)
Requires-Dist: codecov (>=2.0.15)
